amset/__init__.py
amset/constants.py
amset/defaults.yaml
amset/io.py
amset/log.py
amset/util.py
amset/core/__init__.py
amset/core/data.py
amset/core/run.py
amset/core/transport.py
amset/deformation/__init__.py
amset/deformation/common.py
amset/deformation/generation.py
amset/deformation/io.py
amset/deformation/potentials.py
amset/electronic_structure/__init__.py
amset/electronic_structure/common.py
amset/electronic_structure/dos.py
amset/electronic_structure/fd.py
amset/electronic_structure/kpoints.py
amset/electronic_structure/symmetry.py
amset/electronic_structure/tetrahedron.py
amset/interpolation/__init__.py
amset/interpolation/bandstructure.py
amset/interpolation/boltztrap.py
amset/interpolation/deformation.py
amset/interpolation/momentum.py
amset/interpolation/periodic.py
amset/interpolation/projections.py
amset/interpolation/quad.json
amset/interpolation/quad.py
amset/interpolation/wavefunction.py
amset/plot/__init__.py
amset/plot/amset_base.mplstyle
amset/plot/base.py
amset/plot/convergence.py
amset/plot/cumulative.py
amset/plot/electronic_structure.py
amset/plot/lineshape.py
amset/plot/mobility.py
amset/plot/rates.py
amset/plot/revtex.mplstyle
amset/plot/transport.py
amset/scattering/__init__.py
amset/scattering/basic.py
amset/scattering/calculate.py
amset/scattering/common.py
amset/scattering/elastic.py
amset/scattering/inelastic.py
amset/tools/__init__.py
amset/tools/cli.py
amset/tools/common.py
amset/tools/deformation.py
amset/tools/effmass.py
amset/tools/phonon_frequency.py
amset/tools/plot.py
amset/tools/run.py
amset/tools/wavefunction.py
amset/wavefunction/__init__.py
amset/wavefunction/common.py
amset/wavefunction/io.py
amset/wavefunction/pawpyseed.py
amset/wavefunction/vasp.py
amset-0.5.1.data/data/LICENSE
amset-0.5.1.dist-info/licenses/LICENSE
tests/__init__.py
tests/conftest.py
tests/test_io.py
tests/test_util.py
tests/core/__init__.py
tests/core/test_run.py
tests/electronic_structure/__init__.py
tests/electronic_structure/test_common.py
tests/electronic_structure/test_symmetry.py
amset-0.5.1.dist-info/METADATA
amset-0.5.1.dist-info/WHEEL
amset-0.5.1.dist-info/entry_points.txt
amset-0.5.1.dist-info/top_level.txt
amset-0.5.1.dist-info/RECORD
